savekit/__init__.py
savekit/core.py
savekit-2.0.2.dist-info/licenses/LICENSE
test/__init__.py
test/test_savekit.py
savekit-2.0.2.dist-info/METADATA
savekit-2.0.2.dist-info/WHEEL
savekit-2.0.2.dist-info/top_level.txt
savekit-2.0.2.dist-info/RECORD
