Metadata-Version: 2.4
Name: savekit
Version: 2.0.2
Summary: A lightweight, persistent key-value storage toolkit for Python projects, using SQLite via SQLAlchemy. Supports storing primitive types, complex objects, and Pydantic models with full context manager support and project-root storage.
Author: Jose Luis Coyotzi
Author-email: Jose Luis Coyotzi <jlci811122@gmail.com>
License: MIT
Classifier: Programming Language :: Python :: 3
Classifier: License :: OSI Approved :: MIT License
Classifier: Operating System :: OS Independent
Requires-Python: >=3.7
License-File: LICENSE
Requires-Dist: SQLAlchemy>=2.0.0
Requires-Dist: pydantic>=1.10.0
Dynamic: author
Dynamic: license-file
Dynamic: requires-python
